pyanimeplanet/__init__.py
pyanimeplanet/pyanimeplanet.py
pyanimeplanet-1.0.0.dist-info/LICENSE
pyanimeplanet-1.0.0.dist-info/METADATA
pyanimeplanet-1.0.0.dist-info/WHEEL
pyanimeplanet-1.0.0.dist-info/top_level.txt
pyanimeplanet-1.0.0.dist-info/RECORD
