Metadata-Version: 2.1
Name: pyanimeplanet
Version: 1.0.0
Summary: A python module to extract information from anime-planet website
Home-page: UNKNOWN
Author: Vishal Rashmika
Author-email: <vishal.rashmika.perera@gmail.com>
License: UNKNOWN
Keywords: python,web-scraping,animeplanet,anime
Platform: UNKNOWN
Classifier: License :: OSI Approved :: GNU General Public License v3 (GPLv3)
Classifier: Development Status :: 4 - Beta
Classifier: Intended Audience :: Developers
Classifier: Programming Language :: Python :: 3.8
Classifier: Operating System :: Unix
Requires-Dist: bs4
Requires-Dist: selenium (==4.23.1)
